winusbcdc/__init__.py
winusbcdc/__main__.py
winusbcdc/__version__.py
winusbcdc/usb_cdc.py
winusbcdc/winusb.py
winusbcdc/winusbclasses.py
winusbcdc/winusberror.py
winusbcdc/winusbpy.py
winusbcdc/winusbutils.py
WinUsbCDC-1.6.dist-info/LICENSE
WinUsbCDC-1.6.dist-info/METADATA
WinUsbCDC-1.6.dist-info/WHEEL
WinUsbCDC-1.6.dist-info/top_level.txt
WinUsbCDC-1.6.dist-info/RECORD
