Metadata-Version: 2.1
Name: WinUsbCDC
Version: 1.6
Summary: Python package for communicating with USB / CDC devices on windows via the WinUsb driver
Home-page: https://gitlab.com/alelec/winusbcdc
Author: Andrew Leech
Author-email: andrew@alelec.net
License: MIT
License-File: LICENSE
